MANIFEST.in
README.md
setup.py
streamlit_seqviz/__init__.py
streamlit_seqviz/pypi_readme.md
streamlit_seqviz.egg-info/PKG-INFO
streamlit_seqviz.egg-info/SOURCES.txt
streamlit_seqviz.egg-info/dependency_links.txt
streamlit_seqviz.egg-info/requires.txt
streamlit_seqviz.egg-info/top_level.txt
streamlit_seqviz/frontend/dist/index.html
streamlit_seqviz/frontend/dist/vite.svg
streamlit_seqviz/frontend/dist/assets/index-2420fc27.js