Metadata-Version: 2.1
Name: streamlit-seqviz
Version: 0.0.5
Summary: This library is a streamlit app for chemical or medical use that show DNA sequences effectively
Home-page: https://gitlab.com/nicolalandro/streamlit-seqviz
Author: Nicola Landro
Author-email: nicolaxx94@live.it
License: UNKNOWN
Project-URL: Source, https://gitlab.com/nicolalandro/streamlit-seqviz
Keywords: dna,streamlit,chemistry
Platform: UNKNOWN
Requires-Python: >=3.6
